{
  "items": [
    {
      "name": "Coffee",
      "icon": "Coffee.webp"
    },
    {
      "name": "Gazpacho",
      "icon": "Gazpacho.webp"
    },
    {
      "name": "Lemon Pie",
      "icon": "Lemon_pie.webp"
    },
    {
      "name": "Middlemist",
      "icon": "Middlemist.webp"
    },
    {
      "name": "Mistril Ingot",
      "icon": "Mistril_Ingot.webp"
    },
    {
      "name": "Peaches & Cream",
      "icon": "Peaches_and_cream.webp"
    },
    {
      "name": "Perfect Pink Diamond",
      "icon": "Perfect_pink_diamond.webp"
    },
    {
      "name": "Plum Blossom",
      "icon": "Plum_blossom.webp"
    },
    {
      "name": "Pumpkin Pie",
      "icon": "Pumpkin_pie.webp"
    },
    {
      "name": "Tea with Lemon",
      "icon": "Cup_of_tea.webp"
    },
    {
      "name": "Candied Lemon Peel",
      "icon": "Candied_lemon_peel.webp"
    },
    {
      "name": "Diamond",
      "icon": "Diamond.webp"
    },
    {
      "name": "Heather",
      "icon": "Heather.webp"
    },
    {
      "name": "Lemon",
      "icon": "Lemon.webp"
    },
    {
      "name": "Lemon Cake",
      "icon": "Lemon_cake.webp"
    },
    {
      "name": "Lemonade",
      "icon": "Lemonade.webp"
    },
    {
      "name": "Mistril Ore",
      "icon": "Mistril_Ore.webp"
    },
    {
      "name": "Paper",
      "icon": "Paper.webp"
    },
    {
      "name": "Peach",
      "icon": "Peach.webp"
    },
    {
      "name": "Pineshroom Toast",
      "icon": "Pineshroom_toast.webp"
    },
    {
      "name": "Pink Diamond",
      "icon": "Pink_diamond.webp"
    },
    {
      "name": "Pumpkin Stew",
      "icon": "Pumpkin_stew.webp"
    },
    {
      "name": "Red Wine",
      "icon": "Red_Wine.webp"
    },
    {
      "name": "Snapdragon",
      "icon": "Snapdragon.webp"
    },
    {
      "name": "Spicy Cheddar Biscuit",
      "icon": "Spicy_cheddar_biscuit.webp"
    },
    {
      "name": "Tulip",
      "icon": "Tulip.webp"
    },
    {
      "name": "Vegetable Soup",
      "icon": "Vegetable_soup.webp"
    },
    {
      "name": "White Wine",
      "icon": "White_wine.webp"
    },
    {
      "name": "Wild Berry Pie",
      "icon": "Wild_berry_pie.webp"
    },
    {
      "name": "Wild Berry Scone",
      "icon": "Wild_berry_scone.webp"
    },
    {
      "name": "Alda Gem Bracelet",
      "icon": "Alda_gem_bracelet.webp"
    },
    {
      "name": "Apple Honey Curry",
      "icon": "Apple_honey_curry.webp"
    },
    {
      "name": "Chili Coconut Curry",
      "icon": "Chili_coconut_curry.webp"
    },
    {
      "name": "Deluxe Curry",
      "icon": "Deluxe_curry.webp"
    },
    {
      "name": "Family Crest Pendant",
      "icon": "Family_crest_pendant.webp"
    },
    {
      "name": "Perfect Diamond",
      "icon": "Perfect_diamond.webp"
    },
    {
      "name": "Perfect Emerald",
      "icon": "Perfect_emerald.webp"
    },
    {
      "name": "Perfect Ruby",
      "icon": "Perfect_ruby.webp"
    },
    {
      "name": "Perfect Sapphire",
      "icon": "Perfect_sapphire.webp"
    },
    {
      "name": "Cauliflower Curry",
      "icon": "Cauliflower_curry.webp"
    },
    {
      "name": "Chickpea Curry",
      "icon": "Chickpea_curry.webp"
    },
    {
      "name": "Crystal Rose",
      "icon": "Crystal_rose.webp"
    },
    {
      "name": "Emerald",
      "icon": "Emerald.webp"
    },
    {
      "name": "Fog Orchid",
      "icon": "Fog_orchid.webp"
    },
    {
      "name": "Frost Lily",
      "icon": "Frost_lily.webp"
    },
    {
      "name": "Gold Ingot",
      "icon": "Gold_Ingot.webp"
    },
    {
      "name": "Gold Ore",
      "icon": "Gold_Ore.webp"
    },
    {
      "name": "Golden Cheesecake",
      "icon": "Golden_cheesecake.webp"
    },
    {
      "name": "Golden Cookies",
      "icon": "Golden_cookies.webp"
    },
    {
      "name": "Jasmine",
      "icon": "Jasmine.webp"
    },
    {
      "name": "Perfect Gold Ore",
      "icon": "Perfect_gold_ore.webp"
    },
    {
      "name": "Rose",
      "icon": "Rose.webp"
    },
    {
      "name": "Ruby",
      "icon": "Ruby.webp"
    },
    {
      "name": "Rusted Treasure Chest",
      "icon": "Rusted_treasure_chest.webp"
    },
    {
      "name": "Sapphire",
      "icon": "Sapphire.webp"
    },
    {
      "name": "Sapphire Betta",
      "icon": "Sapphire_betta.webp"
    },
    {
      "name": "Snowdrop Anemone",
      "icon": "Snowdrop_anemone.webp"
    },
    {
      "name": "Breath of Fire",
      "icon": "Breath_of_flame.webp"
    },
    {
      "name": "Essence Blossom",
      "icon": "Essence_blossom.webp"
    },
    {
      "name": "Hydrangea",
      "icon": "Hydrangea.webp"
    },
    {
      "name": "Spring Galette",
      "icon": "Spring_galette.webp"
    },
    {
      "name": "Catmint",
      "icon": "Catmint.webp"
    },
    {
      "name": "Celosia",
      "icon": "Celosia.webp"
    },
    {
      "name": "Chysanthemum",
      "icon": "Chrysanthemum.webp"
    },
    {
      "name": "Cosmos",
      "icon": "Cosmos.webp"
    },
    {
      "name": "Crocus",
      "icon": "Crocus.webp"
    },
    {
      "name": "Daffodil",
      "icon": "Daffodil.webp"
    },
    {
      "name": "Daisy",
      "icon": "Daisy.webp"
    },
    {
      "name": "Dandelion",
      "icon": "Dandelion.webp"
    },
    {
      "name": "Iris",
      "icon": "Iris.webp"
    },
    {
      "name": "Lilac",
      "icon": "Lilac.webp"
    },
    {
      "name": "Marigold",
      "icon": "Marigold.webp"
    },
    {
      "name": "Poinsettia",
      "icon": "Poinsettia.webp"
    },
    {
      "name": "Rose Tea",
      "icon": "Rose_tea.webp"
    },
    {
      "name": "Spring Salad",
      "icon": "Spring_salad.png"
    },
    {
      "name": "Sunflower",
      "icon": "Sunflower.webp"
    },
    {
      "name": "Viola",
      "icon": "Viola.webp"
    },
    {
      "name": "Chocolate Cake",
      "icon": "Chocolate_cake.webp"
    },
    {
      "name": "Coconut Cream Pie",
      "icon": "Coconut_cream_pie.webp"
    },
    {
      "name": "Glowberry Cookies",
      "icon": "Glowberry_cookies.webp"
    },
    {
      "name": "Ice Cream Sundae",
      "icon": "Ice_cream_sundae.webp"
    },
    {
      "name": "Mont Blanc",
      "icon": "Mont_blanc.webp"
    },
    {
      "name": "Spell Fruit Parfait",
      "icon": "Spell_fruit_parfait.webp"
    },
    {
      "name": "Strawberry Shortcake",
      "icon": "Strawberry_shortcake.webp"
    },
    {
      "name": "Apple Pie",
      "icon": "Apple_pie.webp"
    },
    {
      "name": "Berries and Cream",
      "icon": "Berries_and_cream.webp"
    },
    {
      "name": "Candied Strawberries",
      "icon": "Candied_strawberries.webp"
    },
    {
      "name": "Caramelized Moon Fruit",
      "icon": "Caramelized_moon_fruit.webp"
    },
    {
      "name": "Caramel Candy",
      "icon": "Caramel_candy.webp"
    },
    {
      "name": "Cherry Cobbler",
      "icon": "Cherry_cobbler.webp"
    },
    {
      "name": "Cherry Tart",
      "icon": "Cherry_tart.webp"
    },
    {
      "name": "Chocolate",
      "icon": "Chocolate.webp"
    },
    {
      "name": "Crystal Berry Pie",
      "icon": "Crystal_berry_pie.webp"
    },
    {
      "name": "Peaches and Cream",
      "icon": "Peaches_and_cream.webp"
    },
    {
      "name": "Pomegranate Sorbet",
      "icon": "Pomegranate_sorbet.webp"
    },
    {
      "name": "Pudding",
      "icon": "Pudding.webp"
    },
    {
      "name": "Roasted Rice Tea",
      "icon": "Roasted_rice_tea.webp"
    },
    {
      "name": "Strawberries and Cream",
      "icon": "Strawberries_and_cream.webp"
    },
    {
      "name": "Sweet Sesame Balls",
      "icon": "Sweet_sesame_balls.webp"
    },
    {
      "name": "Wintergreen Ice Cream",
      "icon": "Wintergreen_ice_cream.webp"
    },
    {
      "name": "Black Tablet",
      "icon": "Black_tablet.webp"
    },
    {
      "name": "Fish Tacos",
      "icon": "Fish_tacos.webp"
    },
    {
      "name": "Hardened Essence",
      "icon": "Hardened_essence.webp"
    },
    {
      "name": "Moon Fruit Cake",
      "icon": "Moon_fruit_cake.webp"
    },
    {
      "name": "Mushroom Brew",
      "icon": "Mushroom_brew.webp"
    },
    {
      "name": "Pizza",
      "icon": "Pizza.webp"
    },
    {
      "name": "Crunchy Chickpeas",
      "icon": "Crunchy_chickpeas.webp"
    },
    {
      "name": "Crystal",
      "icon": "Crystal.webp"
    },
    {
      "name": "Frog",
      "icon": "Frog.webp"
    },
    {
      "name": "Latte",
      "icon": "Latte.webp"
    },
    {
      "name": "Monster Powder",
      "icon": "Monster_powder.webp"
    },
    {
      "name": "Morel Mushroom",
      "icon": "Morel_mushroom.webp"
    },
    {
      "name": "Nettle",
      "icon": "Nettle.webp"
    },
    {
      "name": "Newt",
      "icon": "Newt.webp"
    },
    {
      "name": "Night Queen",
      "icon": "Night_queen.webp"
    },
    {
      "name": "Red Toadstool",
      "icon": "Red_toadstool.webp"
    },
    {
      "name": "Shadow Flower",
      "icon": "Shadow_flower.webp"
    },
    {
      "name": "Spell Fruit",
      "icon": "Spell_fruit.webp"
    },
    {
      "name": "Toasted Sunflower Seeds",
      "icon": "Toasted_sunflower_seeds.webp"
    },
    {
      "name": "Water Chestnut Fritters",
      "icon": "Water_chestnut_fritters.webp"
    },
    {
      "name": "Golden Butter",
      "icon": "Golden_butter.webp"
    },
    {
      "name": "Golden Cheese",
      "icon": "Golden_cheese.webp"
    },
    {
      "name": "Golden Duck Egg",
      "icon": "Golden_duck_egg.webp"
    },
    {
      "name": "Golden Duck Mayonnaise",
      "icon": "Golden_duck_mayonnaise.webp"
    },
    {
      "name": "Golden Egg",
      "icon": "Golden_egg.webp"
    },
    {
      "name": "Golden Mayonnaise",
      "icon": "Golden_mayonnaise.webp"
    },
    {
      "name": "Golden Milk",
      "icon": "Golden_milk.webp"
    },
    {
      "name": "Stone Horse",
      "icon": "Stone_horse.webp"
    },
    {
      "name": "Vegetable Quiche",
      "icon": "Vegetable_quiche.webp"
    },
    {
      "name": "Butter",
      "icon": "Butter.webp"
    },
    {
      "name": "Cheese",
      "icon": "Cheese.webp"
    },
    {
      "name": "Duck Egg",
      "icon": "Duck_egg.webp"
    },
    {
      "name": "Duck Mayonnaise",
      "icon": "Duck_mayonnaise.webp"
    },
    {
      "name": "Loaded Baked Potato",
      "icon": "Loaded_baked_potato.webp"
    },
    {
      "name": "Mayonnaise",
      "icon": "Mayonnaise.webp"
    },
    {
      "name": "Milk",
      "icon": "Milk.webp"
    },
    {
      "name": "Mushroom Steak Dinner",
      "icon": "Mushroom_steak_dinner.webp"
    },
    {
      "name": "Quiche",
      "icon": "Quiche.webp"
    },
    {
      "name": "Sweet Potato Pie",
      "icon": "Sweet_potato_pie.webp"
    },
    {
      "name": "Vegetable Pot Pie",
      "icon": "Vegetable_pot_pie.webp"
    },
    {
      "name": "Breaded Catfish",
      "icon": "Breaded_catfish.webp"
    },
    {
      "name": "Cabbage Slaw",
      "icon": "Cabbage_slaw.webp"
    },
    {
      "name": "Incredibly Hot Pot",
      "icon": "Incredibly_hot_pot.webp"
    },
    {
      "name": "Rosemary Garlic Noodles",
      "icon": "Rosemary_garlic_noodles.webp"
    },
    {
      "name": "Seafood Boil",
      "icon": "Seafood_boil.webp"
    },
    {
      "name": "Seafood Snow Pea Noodles",
      "icon": "Seafood_snow_pea_noodles.webp"
    },
    {
      "name": "Sushi Platter",
      "icon": "Sushi_platter.png"
    },
    {
      "name": "Cod with Thyme",
      "icon": "Cod_with_thyme.webp"
    },
    {
      "name": "Deep Sea Soup",
      "icon": "Deep_sea_soup.webp"
    },
    {
      "name": "Flour",
      "icon": "Flour.webp"
    },
    {
      "name": "Garlic",
      "icon": "Garlic.webp"
    },
    {
      "name": "Garlic Bread",
      "icon": "Garlic_bread.webp"
    },
    {
      "name": "Grilled Cheese",
      "icon": "Grilled_cheese.webp"
    },
    {
      "name": "Iced Coffee",
      "icon": "Iced_coffee.webp"
    },
    {
      "name": "Miner's Mushroom Stew",
      "icon": "Miner's_mushroom_stew.webp"
    },
    {
      "name": "Rice",
      "icon": "Rice.webp"
    },
    {
      "name": "Sugar",
      "icon": "Sugar.webp"
    },
    {
      "name": "Turnip and Potato Gratin",
      "icon": "Turnip_and_potato_gratin.webp"
    },
    {
      "name": "Upper Mines Mushroom",
      "icon": "Upper_mines_mushroom.webp"
    },
    {
      "name": "Meteorite",
      "icon": "Meteorite.webp"
    },
    {
      "name": "Perfect Copper Ore",
      "icon": "Perfect_copper_ore.webp"
    },
    {
      "name": "Perfect Iron Ore",
      "icon": "Perfect_iron_ore.webp"
    },
    {
      "name": "Perfect Mistril Ore",
      "icon": "Perfect_mistril_ore.webp"
    },
    {
      "name": "Perfect Silver Ore",
      "icon": "Perfect_silver_ore.webp"
    },
    {
      "name": "Beer",
      "icon": "Beer.webp"
    },
    {
      "name": "Copper Ingot",
      "icon": "Copper_Ingot.webp"
    },
    {
      "name": "Copper Ore",
      "icon": "Copper_Ore.webp"
    },
    {
      "name": "Grilled Eel Rice Bowl",
      "icon": "Grilled_eel_rice_bowl.webp"
    },
    {
      "name": "Hot Chocolate",
      "icon": "Hot_chocolate.webp"
    },
    {
      "name": "Iron Ingot",
      "icon": "Iron_Ingot.webp"
    },
    {
      "name": "Iron Ore",
      "icon": "Iron_Ore.webp"
    },
    {
      "name": "Mocha",
      "icon": "Mocha.webp"
    },
    {
      "name": "Perch Risotto",
      "icon": "Perch_risotto.webp"
    },
    {
      "name": "Red Snapper Sushi",
      "icon": "Red_snapper_sushi.webp"
    },
    {
      "name": "Sea Bream Rice",
      "icon": "Sea_bream_rice.webp"
    },
    {
      "name": "Sesame Tuna Bowl",
      "icon": "Sesame_tuna_bowl.webp"
    },
    {
      "name": "Silver Ingot",
      "icon": "Silver_Ingot.webp"
    },
    {
      "name": "Silver Ore",
      "icon": "Silver_Ore.webp"
    },
    {
      "name": "Spicy Crab Sushi",
      "icon": "Spicy_crab_sushi.webp"
    },
    {
      "name": "Golden Bristle",
      "icon": "Golden_bristle.webp"
    },
    {
      "name": "Golden Bull Horn",
      "icon": "Golden_bull_horn.webp"
    },
    {
      "name": "Golden Duck Feather",
      "icon": "Golden_duck_feather.webp"
    },
    {
      "name": "Golden Feather",
      "icon": "Golden_feather.webp"
    },
    {
      "name": "Golden Horse Hair",
      "icon": "Golden_horse_hair.webp"
    },
    {
      "name": "Hard Wood",
      "icon": "Hard_wood.webp"
    },
    {
      "name": "Lobster Roll",
      "icon": "Lobster_roll.webp"
    },
    {
      "name": "Veggie Sub Sandwich",
      "icon": "Veggie_sub_sandwich.webp"
    },
    {
      "name": "Wood",
      "icon": "Wood.webp"
    },
    {
      "name": "Bread",
      "icon": "Bread.webp"
    },
    {
      "name": "Bristle",
      "icon": "Bristle.webp"
    },
    {
      "name": "Bull Horn",
      "icon": "Bull_horn.webp"
    },
    {
      "name": "Clay",
      "icon": "Clay.webp"
    },
    {
      "name": "Cranberry Orange Scone",
      "icon": "Cranberry_orange_scone.webp"
    },
    {
      "name": "Duck Feather",
      "icon": "Duck_feather.webp"
    },
    {
      "name": "Glass",
      "icon": "Glass.webp"
    },
    {
      "name": "Horse Hair",
      "icon": "Horse_hair.webp"
    },
    {
      "name": "Obsidian",
      "icon": "Obsidian.webp"
    },
    {
      "name": "Rooster Feather",
      "icon": "Rooster_feather.webp"
    },
    {
      "name": "Stone",
      "icon": "Stone.webp"
    },
    {
      "name": "Beet",
      "icon": "Beet.webp"
    },
    {
      "name": "Beet Salad",
      "icon": "Beet_salad.webp"
    },
    {
      "name": "Beet Soup",
      "icon": "Beet_soup.webp"
    },
    {
      "name": "Dragon Scale",
      "icon": "Dragon_scale.webp"
    },
    {
      "name": "Harvest Plate",
      "icon": "Harvest_plate.webp"
    },
    {
      "name": "Summer Salad",
      "icon": "Summer_salad.webp"
    },
    {
      "name": "Cucumber",
      "icon": "Cucumber.webp"
    },
    {
      "name": "Cucumber Salad",
      "icon": "Cucumber_salad.webp"
    },
    {
      "name": "Green Tea",
      "icon": "Green_Tea.webp"
    },
    {
      "name": "Herb Salad",
      "icon": "Herb_salad.webp"
    },
    {
      "name": "Honey",
      "icon": "Honey.webp"
    },
    {
      "name": "Pan Fried Salmon",
      "icon": "Pan_fried_salmon.webp"
    },
    {
      "name": "Rose Hip",
      "icon": "Rose_hip.webp"
    },
    {
      "name": "Rosehip Jam",
      "icon": "Rosehip_jam.webp"
    },
    {
      "name": "Rosemary",
      "icon": "Rosemary.webp"
    },
    {
      "name": "Seaweed",
      "icon": "Seaweed.webp"
    },
    {
      "name": "Seaweed Salad",
      "icon": "Seaweed_salad.webp"
    },
    {
      "name": "Sweetroot",
      "icon": "Sweetroot.webp"
    },
    {
      "name": "Underseaweed",
      "icon": "Underseaweed.webp"
    },
    {
      "name": "Alda Bronze Sword",
      "icon": "Alda_bronze_sword.webp"
    },
    {
      "name": "Aldarian Sword",
      "icon": "Aldarian_sword.webp"
    },
    {
      "name": "Apple Juice",
      "icon": "Apple_juice.webp"
    },
    {
      "name": "Bullfrog",
      "icon": "Bullfrog.webp"
    },
    {
      "name": "Caldosian Sword",
      "icon": "Caldosian_sword.webp"
    },
    {
      "name": "Hermit Crab",
      "icon": "Hermit_crab.webp"
    },
    {
      "name": "Jam Sandwich",
      "icon": "Jam_sandwich.webp"
    },
    {
      "name": "Apple",
      "icon": "Apple.webp"
    },
    {
      "name": "Blackberry",
      "icon": "Blackberry.webp"
    },
    {
      "name": "Cattail Fluff",
      "icon": "Cattail_fluff.webp"
    },
    {
      "name": "Grape Juice",
      "icon": "Grape_juice.webp"
    },
    {
      "name": "Lightning Dragonfly",
      "icon": "Lightning_dragonfly.webp"
    },
    {
      "name": "Monster Cookie",
      "icon": "Monster_cookie.webp"
    },
    {
      "name": "Snail",
      "icon": "Snail.webp"
    },
    {
      "name": "Trail Mix",
      "icon": "Trail_mix.webp"
    },
    {
      "name": "Turtle",
      "icon": "Turtle.webp"
    },
    {
      "name": "Catfish",
      "icon": "Catfish.webp"
    },
    {
      "name": "Crystalline Cricket",
      "icon": "Crystalline_cricket.webp"
    },
    {
      "name": "Petrified Wood",
      "icon": "Petrified_wood.webp"
    },
    {
      "name": "Tiny Dinosaur Skeleton",
      "icon": "Tiny_dinosaur_skeleton.webp"
    },
    {
      "name": "Butterfly",
      "icon": "Butterfly.webp"
    },
    {
      "name": "Carrot",
      "icon": "Carrot.webp"
    },
    {
      "name": "Cicada",
      "icon": "Cicada.webp"
    },
    {
      "name": "Cod",
      "icon": "Cod.webp"
    },
    {
      "name": "Cricket",
      "icon": "Cricket.webp"
    },
    {
      "name": "Firefly",
      "icon": "Firefly.webp"
    },
    {
      "name": "Fuzzy Moth",
      "icon": "Fuzzy_moth.webp"
    },
    {
      "name": "Grasshopper",
      "icon": "Grasshopper.webp"
    },
    {
      "name": "Mackerel",
      "icon": "Mackerel.webp"
    },
    {
      "name": "Monster Shell",
      "icon": "Monster_shell.webp"
    },
    {
      "name": "Monster Hoop",
      "icon": "Monster_hoop.webp"
    },
    {
      "name": "Pumpkin",
      "icon": "Pumpkin.webp"
    },
    {
      "name": "Red Snapper",
      "icon": "Red_snapper.webp"
    },
    {
      "name": "Rockroot",
      "icon": "Rockroot.webp"
    },
    {
      "name": "Salmon",
      "icon": "Salmon.webp"
    },
    {
      "name": "Sardine",
      "icon": "Sardine.webp"
    },
    {
      "name": "Sod",
      "icon": "Sod.webp"
    },
    {
      "name": "Tuna",
      "icon": "Tuna.webp"
    },
    {
      "name": "Alda Feather Pendant",
      "icon": "Alda_feather_pendant.webp"
    },
    {
      "name": "Jasmine Tea",
      "icon": "Jasmine_tea.webp"
    },
    {
      "name": "Poached Pear",
      "icon": "Poached_pear.webp"
    },
    {
      "name": "Blackberry Jam",
      "icon": "Blackberry_jam.webp"
    },
    {
      "name": "Blueberry Jam",
      "icon": "Blueberry_jam.webp"
    },
    {
      "name": "Chrysanthemum",
      "icon": "Chrysanthemum.webp"
    },
    {
      "name": "Marmalade",
      "icon": "Marmalade.webp"
    },
    {
      "name": "Moon Fruit Cake",
      "icon": "Moon_fruit_cake.webp"
    },
    {
      "name": "Wild Berry Jam",
      "icon": "Wild_berry_jam.webp"
    },
    {
      "name": "Baked Sweetroot",
      "icon": "Baked_sweetroot.webp"
    },
    {
      "name": "Braised Burdock",
      "icon": "Braised_burdock.webp"
    },
    {
      "name": "Clam Chowder",
      "icon": "Clam_chowder.webp"
    },
    {
      "name": "Fish Skewer",
      "icon": "Fish_skewer.webp"
    },
    {
      "name": "Miner's Helmet",
      "icon": "Miner's_helmet.webp"
    },
    {
      "name": "Pan Fried Bream",
      "icon": "Pan_fried_bream.webp"
    },
    {
      "name": "Shard Mass",
      "icon": "Shard_mass.webp"
    },
    {
      "name": "Canned Sardines",
      "icon": "Canned_sardines.webp"
    },
    {
      "name": "Fish Stew",
      "icon": "Fish_stew.webp"
    },
    {
      "name": "Hot Toddy",
      "icon": "Hot_toddy.webp"
    },
    {
      "name": "Pear",
      "icon": "Pear.webp"
    },
    {
      "name": "Peat",
      "icon": "Peat.webp"
    },
    {
      "name": "Pomegranate",
      "icon": "Pomegranate.webp"
    },
    {
      "name": "Caldosian Drinking Horn",
      "icon": "Caldosian_drinking_horn.webp"
    },
    {
      "name": "Crayfish Etouffee",
      "icon": "Crayfish_etouffee.webp"
    },
    {
      "name": "Crispy Fried Earthshroom",
      "icon": "Crispy_fried_earthshroom.webp"
    },
    {
      "name": "Spicy Corn",
      "icon": "Spicy_corn.png"
    },
    {
      "name": "Wild Grapes",
      "icon": "Wild_grapes.webp"
    },
    {
      "name": "Basil",
      "icon": "Basil.webp"
    },
    {
      "name": "Chili Pepper",
      "icon": "Chili_pepper.webp"
    },
    {
      "name": "Dried Squid",
      "icon": "Dried_squid.webp"
    },
    {
      "name": "Roasted Chestnuts",
      "icon": "Roasted_chestnuts.webp"
    },
    {
      "name": "Rock Salt",
      "icon": "Rock_salt.webp"
    },
    {
      "name": "Sesame Broccoli",
      "icon": "Sesame_broccoli.webp"
    },
    {
      "name": "Spicy Water Chestnuts",
      "icon": "Spicy_water_chestnuts.webp"
    },
    {
      "name": "Tea",
      "icon": "Tea.webp"
    },
    {
      "name": "Thyme",
      "icon": "Thyme.webp"
    },
    {
      "name": "Baked Potato",
      "icon": "Baked_potato.webp"
    },
    {
      "name": "Narrows Moss",
      "icon": "Narrows_moss.webp"
    },
    {
      "name": "Watermelon",
      "icon": "Watermelon.webp"
    },
    {
      "name": "Wheat",
      "icon": "Wheat.webp"
    },
    {
      "name": "Broccoli",
      "icon": "Broccoli.webp"
    },
    {
      "name": "Cabbage",
      "icon": "Cabbage.webp"
    },
    {
      "name": "Cauliflower",
      "icon": "Cauliflower.webp"
    },
    {
      "name": "Corn",
      "icon": "Corn.webp"
    },
    {
      "name": "Cranberry",
      "icon": "Cranberry.webp"
    },
    {
      "name": "Daikon Radish",
      "icon": "Daikon_radish.webp"
    },
    {
      "name": "Onion",
      "icon": "Onion.webp"
    },
    {
      "name": "Peas",
      "icon": "Peas.webp"
    },
    {
      "name": "Potato",
      "icon": "Potato.webp"
    },
    {
      "name": "Rice Stalk",
      "icon": "Rice_stalk.webp"
    },
    {
      "name": "Snow Peas",
      "icon": "Snow_peas.webp"
    },
    {
      "name": "Strawberry",
      "icon": "Strawberry.webp"
    },
    {
      "name": "Sugar Cane",
      "icon": "Sugar_cane.webp"
    },
    {
      "name": "Sweet Potato",
      "icon": "Sweet_potato.webp"
    },
    {
      "name": "Turnip",
      "icon": "Turnip.webp"
    },
    {
      "name": "Berry Bowl",
      "icon": "Berry_bowl.webp"
    },
    {
      "name": "Deluxe Small Animal Feed",
      "icon": "Deluxe_small_animal_feed.webp"
    },
    {
      "name": "Glowberry",
      "icon": "Glowberry.webp"
    },
    {
      "name": "Grilled Corn",
      "icon": "Grilled_corn.webp"
    },
    {
      "name": "Quality Small Animal Feed",
      "icon": "Quality_small_animal_feed.webp"
    },
    {
      "name": "Shiny Bead",
      "icon": "Shiny_bead.webp"
    },
    {
      "name": "Ultimate Small Animal Feed",
      "icon": "Ultimate_small_animal_feed.webp"
    },
    {
      "name": "Blueberry",
      "icon": "Blueberry.webp"
    },
    {
      "name": "Cherry",
      "icon": "Cherry.webp"
    },
    {
      "name": "Chestnut",
      "icon": "Chestnut.webp"
    },
    {
      "name": "Coconut",
      "icon": "Coconut.webp"
    },
    {
      "name": "Grass Seed",
      "icon": "Grass_seed.webp"
    },
    {
      "name": "Moon Fruit",
      "icon": "Moon_fruit.webp"
    },
    {
      "name": "Orange",
      "icon": "Orange.webp"
    },
    {
      "name": "Wild Berries",
      "icon": "Wild_berries.webp"
    },
    {
      "name": "Wintergreen Berry",
      "icon": "Wintergreen_berry.webp"
    },
    {
      "name": "Lavender Tea",
      "icon": "Lavender_tea.webp"
    },
    {
      "name": "Curry Powder",
      "icon": "Curry_powder.webp"
    },
    {
      "name": "Oil",
      "icon": "Oil.webp"
    },
    {
      "name": "Soy Sauce",
      "icon": "Soy_sauce.webp"
    },
    {
      "name": "Coconut Milk",
      "icon": "Coconut_milk.webp"
    },
    {
      "name": "Shards",
      "icon": "Shards.webp"
    },
    {
      "name": "Tomato Soup",
      "icon": "Tomato_soup.webp"
    },
    {
      "name": "Amber Trapped Insect",
      "icon": "Amber_trapped_insect.webp"
    },
    {
      "name": "Bumblebee",
      "icon": "Bumblebee.webp"
    },
    {
      "name": "Fairy Bee",
      "icon": "Fairy_bee.webp"
    },
    {
      "name": "Jewel Beetle",
      "icon": "Jewel_beetle.webp"
    },
    {
      "name": "Rhinoceros Beetle",
      "icon": "Rhinoceros_beetle.webp"
    },
    {
      "name": "Roly Poly",
      "icon": "Roly_poly.webp"
    },
    {
      "name": "Sea Scarab",
      "icon": "Sea_scarab.webp"
    },
    {
      "name": "Strobe Firefly",
      "icon": "Strobe_firefly.webp"
    },
    {
      "name": "Ant",
      "icon": "Ant.webp"
    },
    {
      "name": "Cave Shrimp",
      "icon": "Cave_shrimp.webp"
    },
    {
      "name": "Hummingbird Hawk Moth",
      "icon": "Hummingbird_hawk_moth.webp"
    },
    {
      "name": "Inchworm",
      "icon": "Inchworm.webp"
    },
    {
      "name": "Mistmoth",
      "icon": "Mistmoth.webp"
    },
    {
      "name": "Monarch Butterfly",
      "icon": "Monarch_butterfly.webp"
    },
    {
      "name": "Orchid Mantis",
      "icon": "Orchid_mantis.webp"
    },
    {
      "name": "Pond Skater",
      "icon": "Pond_Skater.webp"
    },
    {
      "name": "Praying Mantis",
      "icon": "Praying_mantis.webp"
    },
    {
      "name": "Puddle Spider",
      "icon": "Puddle_spider.webp"
    },
    {
      "name": "River Snail",
      "icon": "River_snail.webp"
    },
    {
      "name": "Snowball Beetle",
      "icon": "Snowball_beetle.webp"
    },
    {
      "name": "Worm",
      "icon": "Worm.webp"
    },
    {
      "name": "Ancient Horn Circlet",
      "icon": "Ancient_horn_circlet.webp"
    },
    {
      "name": "Lost Crown Of Aldaria",
      "icon": "Lost_crown_of_aldaria.webp"
    },
    {
      "name": "Stone Shell",
      "icon": "Stone_shell.webp"
    },
    {
      "name": "Blue Conch Shell",
      "icon": "Blue_conch_shell.webp"
    },
    {
      "name": "Pink Scallop Shell",
      "icon": "Pink_scallop_shell.webp"
    },
    {
      "name": "Sand Dollar",
      "icon": "Sand_dollar.webp"
    },
    {
      "name": "Spirula Shell",
      "icon": "Spirula_shell.webp"
    },
    {
      "name": "Ancient Gold Coin",
      "icon": "Ancient_gold_coin.webp"
    },
    {
      "name": "Fried Rice",
      "icon": "Fried_rice.webp"
    },
    {
      "name": "Onion Soup",
      "icon": "Onion_soup.webp"
    },
    {
      "name": "Peaches And Cream",
      "icon": "Peaches_and_cream.webp"
    },
    {
      "name": "Roasted Cauliflower",
      "icon": "Roasted_cauliflower.webp"
    },
    {
      "name": "Roasted Sweet Potato",
      "icon": "Roasted_sweet_potato.webp"
    },
    {
      "name": "Sauteed Snow Peas",
      "icon": "Sauteed_snow_peas.webp"
    },
    {
      "name": "Braised Carrots",
      "icon": "Braised_carrots.webp"
    },
    {
      "name": "Salted Watermelon",
      "icon": "Salted_watermelon.webp"
    },
    {
      "name": "Simmered Daikon",
      "icon": "Simmered_daikon.webp"
    },
    {
      "name": "Sliced Turnip",
      "icon": "Sliced_turnip.webp"
    },
    {
      "name": "Strawberries And Cream",
      "icon": "Strawberries_and_cream.webp"
    },
    {
      "name": "Hard Boiled Egg",
      "icon": "Hard_boiled_egg.webp"
    },
    {
      "name": "Obsidian Blade",
      "icon": "Obsidian_blade.webp"
    },
    {
      "name": "Rock Statue",
      "icon": "Rock_statue.webp"
    },
    {
      "name": "Rock With A Hole",
      "icon": "Rock_with_a_hole.webp"
    },
    {
      "name": "Weightless Stone",
      "icon": "Weightless_stone.webp"
    },
    {
      "name": "Giant Fish Scale",
      "icon": "Giant_fish_scale.webp"
    },
    {
      "name": "Rubber Fish",
      "icon": "Rubber_fish.webp"
    },
    {
      "name": "Grilled Eel Rice bowl",
      "icon": "Grilled_eel_rice_bowl.webp"
    },
    {
      "name": "Horseradish Salmon",
      "icon": "Horseradish_salmon.png"
    },
    {
      "name": "Mackerel Sashimi",
      "icon": "Mackerel_sashimi.webp"
    },
    {
      "name": "Pan Fried Bream",
      "icon": "Pan_fried_bream.webp"
    },
    {
      "name": "Pan Fried Salmon",
      "icon": "Pan_fried_salmon.webp"
    },
    {
      "name": "Pan Fried Snapper",
      "icon": "Pan_fried_snapper.webp"
    },
    {
      "name": "Salmon Sashimi",
      "icon": "Salmon_sashimi.webp"
    },
    {
      "name": "Smoked Trout Soup",
      "icon": "Smoked_trout_soup.webp"
    },
    {
      "name": "Tuna Sashimi",
      "icon": "Tuna_sashimi.webp"
    },
    {
      "name": "Crystal Berries",
      "icon": "Crystal_berries.webp"
    },
    {
      "name": "Chicken Egg",
      "icon": "Chicken_egg.webp"
    },
    {
      "name": "Moon Fruit",
      "icon": "Moon_fruit.webp"
    },
    {
      "name": "Golden Alpaca Wool",
      "icon": "Golden_alpaca_wool.webp"
    },
    {
      "name": "Golden Rabbit Wool",
      "icon": "Golden_rabbit_wool.webp"
    },
    {
      "name": "Golden Sheep Wool",
      "icon": "Golden_sheep_wool.webp"
    },
    {
      "name": "Alpaca Wool",
      "icon": "Alpaca_wool.webp"
    },
    {
      "name": "Breath Of Fire",
      "icon": "Breath_of_flame.webp"
    },
    {
      "name": "Rabbit Wool",
      "icon": "Rabbit_wool.webp"
    },
    {
      "name": "Sheep Wool",
      "icon": "Sheep_wool.webp"
    },
    {
      "name": "Coral",
      "icon": "Coral.webp"
    },
    {
      "name": "Hard Wood",
      "icon": "Hard_wood.webp"
    },
    {
      "name": "Winter Stew",
      "icon": "Winter_stew.webp"
    },
    {
      "name": "Cranberry Juice",
      "icon": "Cranberry_juice.webp"
    },
    {
      "name": "Orange Juice",
      "icon": "Orange_juice.webp"
    },
    {
      "name": "Pomegranate Juice",
      "icon": "Pomegranate_juice.webp"
    },
    {
      "name": "Steamed Broccoli",
      "icon": "Steamed_broccoli.webp"
    },
    {
      "name": "Tide Salad",
      "icon": "Tide_salad.webp"
    },
    {
      "name": "Turnip And Cabbage Salad",
      "icon": "Turnip_and_cabbage_salad.webp"
    },
    {
      "name": "Ancient Royal Scepter",
      "icon": "Ancient_royal_scepter.webp"
    },
    {
      "name": "Dog Treat",
      "icon": "Dog_treat.webp"
    },
    {
      "name": "Copper Nugget Beetle",
      "icon": "Copper_nugget_beetle.webp"
    },
    {
      "name": "Crab Cakes",
      "icon": "Crab_cakes.webp"
    },
    {
      "name": "Coin Lump",
      "icon": "Coin_lump.webp"
    },
    {
      "name": "Fiber",
      "icon": "Fiber.webp"
    },
    {
      "name": "Dragon Forged Bracelet",
      "icon": "Dragon_forged_bracelet.webp"
    },
    {
      "name": "Temple Flower",
      "icon": "Temple_flower.webp"
    }
  ],
  "metadata": {
    "totalItems": 417,
    "itemsWithIcons": 417,
    "itemsWithoutIcons": 0,
    "lastUpdated": "2025-08-05T17:37:47.054Z",
    "availableIconFiles": 408,
    "usedIcons": 406,
    "unusedIcons": 2,
    "iconUtilization": 100,
    "totalGiftReferences": 899,
    "dataNormalizationEfficiency": 54,
    "referencedGifts": 412,
    "itemsRemovedLastUpdate": 0,
    "itemsAddedLastUpdate": 0
  }
}